<?xml version="1.0" encoding="UTF-8"?>
<?xml-stylesheet type="text/css" href="../../resources/stylesheets/wasmsgxml.css"?>
<TMSSource name="TivoliMessages" tmsVersion="1.0" xml:lang="en">
<!-- CMVC MSG File Name = /com.ibm.ws.eba.gatewayloader/src/com/ibm/ws/eba/internal/framework/classloading/Messages.nlsprops -->
<!-- DO NOT EDIT THIS FILE - This file was generated by the XML/Html & Property emitter -->
<!-- BEGIN MESSAGES -->
<Message ID="CWSAP0001E" severity="E" prefix="yes">
  <MsgText pgmKey="0001E_CLASS_TRANSFORMATION_ERROR" varFormat="Java">
    0001E_CLASS_TRANSFORMATION_ERROR=CWSAP0001E: Impossibile trasformare la classe {0} dal bundle {1}.
  </MsgText>
  <Explanation>
    Impossibile trasformare una classe al momento del caricamento.
  </Explanation>
  <UserResponse>
    Verificare che la classe esista e che soddisfi i requisiti del trasformatore.
  </UserResponse>
</Message>
<!-- END MESSAGES -->
</TMSSource>
