<?xml version="1.0" encoding="UTF-8"?>
<?xml-stylesheet type="text/css" href="../../resources/stylesheets/wasmsgxml.css"?>
<TMSSource name="TivoliMessages" tmsVersion="1.0" xml:lang="en">
<!-- CMVC MSG File Name = /com.ibm.ws.eba.obr.provisioner/src/com/ibm/ws/eba/provisioning/exception/nls/resolver.nlsprops -->
<!-- DO NOT EDIT THIS FILE - This file was generated by the XML/Html & Property emitter -->
<!-- BEGIN MESSAGES -->
<Message ID="CWSAO0006E" severity="E" prefix="yes">
  <MsgText pgmKey="RESOLVER_UNABLE_TO_REMOVE_CONFIG_REPOSITORY_EXCEPTION" varFormat="Java">
    RESOLVER_UNABLE_TO_REMOVE_CONFIG_REPOSITORY_EXCEPTION=CWSAO0006E: Se ha producido un error interno. No se ha podido eliminar el repositorio configurado con el URL {0} del servicio RepositoryAdmin. Excepci&#243;n: {1}
  </MsgText>
  <Explanation>
    CMSG0001
  </Explanation>
  <UserResponse>
    CMSG0002
  </UserResponse>
</Message>
<Message ID="CWSAO0001E" severity="E" prefix="yes">
  <MsgText pgmKey="RESOLVER_SERVICE_UNAVAILABLE" varFormat="Java">
    RESOLVER_SERVICE_UNAVAILABLE=CWSAO0001E: Se ha producido un error interno. No se ha podido suministrar el archivado EBA (Enterprise Bundle Archive) {0} porque no est&#225; disponible el servicio {1}.
  </MsgText>
  <Explanation>
    CMSG0001
  </Explanation>
  <UserResponse>
    CMSG0002
  </UserResponse>
</Message>
<Message ID="CWSAO0014E" severity="E" prefix="yes">
  <MsgText pgmKey="RESOLVER_UNABLE_TO_LOCATE_RESOURCE" varFormat="Java">
    RESOLVER_UNABLE_TO_LOCATE_RESOURCE=CWSAO0014E: El recurso con el nombre simb&#243;lico {0} y la versi&#243;n {1} no se ha podido identificar en el repositorio.
  </MsgText>
  <Explanation>
    El entorno de ejecuci&#243;n ha intentado identificar alg&#250;n contenido de use-bundle o de aplicaci&#243;n, pero no ha podido encontrar ning&#250;n repositorio de paquetes. La causa m&#225;s probable es que se haya eliminado el contenido del repositorio. Esto significa que la aplicaci&#243;n no podr&#225; resolverse en el futuro.
  </Explanation>
  <UserResponse>
    A&#241;ada el paquete que falta a un repositorio de paquetes configurado.
  </UserResponse>
</Message>
<Message ID="CWSAO0013W" severity="W" prefix="yes">
  <MsgText pgmKey="RESOLVER_UNABLE_TO_ADD_CONFIG_REPOSITORY_WARNING" varFormat="Java">
    RESOLVER_UNABLE_TO_ADD_CONFIG_REPOSITORY_WARNING=CWSAO0013W: No se puede a&#241;adir el repositorio de paquetes con URL {0} al resolvedor. Excepci&#243;n: {1}
  </MsgText>
  <Explanation>
    No se ha podido a&#241;adir un repositorio de paquetes al resolvedor. La causa m&#225;s probable es que el URL del repositorio no es v&#225;lido.
  </Explanation>
  <UserResponse>
    Compruebe que el URL del deposito de paquetes es v&#225;lido y que el repositorio de paquetes tiene el formato correcto.
  </UserResponse>
</Message>
<Message ID="CWSAO0002E" severity="E" prefix="yes">
  <MsgText pgmKey="RESOLVER_IOEXCEPTION" varFormat="Java">
    RESOLVER_IOEXCEPTION=CWSAO0002E: Se ha producido un error interno. No se ha podido suministrar el archivado EBA {0} porque no se ha podido crear el archivo de repositorio local {1}.
  </MsgText>
  <Explanation>
    CMSG0001
  </Explanation>
  <UserResponse>
    CMSG0002
  </UserResponse>
</Message>
<Message ID="CWSAO0004E" severity="E" prefix="yes">
  <MsgText pgmKey="RESOLVER_UNABLE_TO_ADD_CONFIG_REPOSITORY_EXCEPTION" varFormat="Java">
    RESOLVER_UNABLE_TO_ADD_CONFIG_REPOSITORY_EXCEPTION=CWSAO0004E: Se ha producido un error interno. No se ha podido a&#241;adir el repositorio configurado con el URL {0} al servicio RepositoryAdmin. Excepci&#243;n: {1}
  </MsgText>
  <Explanation>
    CMSG0001
  </Explanation>
  <UserResponse>
    CMSG0002
  </UserResponse>
</Message>
<Message ID="CWSAO0003E" severity="E" prefix="yes">
  <MsgText pgmKey="RESOLVER_UNABLE_TO_ADD_REPOSITORY_EXCEPTION" varFormat="Java">
    RESOLVER_UNABLE_TO_ADD_REPOSITORY_EXCEPTION=CWSAO0003E: Se ha producido un error interno. Al suministrar el archivado EBA {0}, no se ha podido a&#241;adir el repositorio {1} al servicio RepositoryAdmin.
  </MsgText>
  <Explanation>
    CMSG0001
  </Explanation>
  <UserResponse>
    CMSG0002
  </UserResponse>
</Message>
<Message ID="CWSAO0007E" severity="E" prefix="yes">
  <MsgText pgmKey="RESOLVER_UNABLE_TO_RESOLVE" varFormat="Java">
    RESOLVER_UNABLE_TO_RESOLVE=CWSAO0007E: El sistema no puede suministrar el EBA {0} porque se han detectado los siguientes problemas en la cadena de dependencia: {1}
  </MsgText>
  <Explanation>
    No se puede resolver el conjunto completo de dependencias de un EBA (Enterprise Bundle Archive).
  </Explanation>
  <UserResponse>
    Consulte los mensajes adjuntos para obtener informaci&#243;n sobre las dependencias que no pueden suministrarse. Corrija los problemas, vuelva a instalar el EBA e int&#233;ntelo de nuevo.
  </UserResponse>
</Message>
<Message ID="CWSAO0005E" severity="E" prefix="yes">
  <MsgText pgmKey="RESOLVER_UNABLE_TO_REMOVE_REPOSITORY_EXCEPTION" varFormat="Java">
    RESOLVER_UNABLE_TO_REMOVE_REPOSITORY_EXCEPTION=CWSAO0005E: Se ha producido un error interno. Al suministrar el archivado EBA {0}, no se ha podido eliminar el repositorio {1} del servicio RepositoryAdmin.
  </MsgText>
  <Explanation>
    CMSG0001
  </Explanation>
  <UserResponse>
    CMSG0002
  </UserResponse>
</Message>
<Message ID="CWSAO0008E" severity="E" prefix="yes">
  <MsgText pgmKey="RESOLVER_UNABLE_HANDLE_FRAGMENT_HOST_WITH_EXTENSION" varFormat="Java">
    RESOLVER_UNABLE_HANDLE_FRAGMENT_HOST_WITH_EXTENSION=CWSAO0008E: No se puede conectar el host de fragmento {0} porque tiene una directiva de extensi&#243;n.
  </MsgText>
  <Explanation>
    No se puede conectar un fragmento que tiene establecida una directiva de extensi&#243;n. Las aplicaciones no deben establecer esta directiva. La directiva de extensi&#243;n se aplica s&#243;lo cuando Fragment-Host es el paquete del sistema.
  </Explanation>
  <UserResponse>
    Elimine la directiva de extensi&#243;n de la aplicaci&#243;n.
  </UserResponse>
</Message>
<!-- END MESSAGES -->
</TMSSource>
