<?xml version="1.0" encoding="UTF-8"?>
<?xml-stylesheet type="text/css" href="../../resources/stylesheets/wasmsgxml.css"?>
<TMSSource name="TivoliMessages" tmsVersion="1.0" xml:lang="en">
<!-- CMVC MSG File Name = BATCH/ws/code/batch.runtime/src/com/ibm/ws/grid/utility/nls/WSBatchPackagerMessages.nlsprops -->
<!-- DO NOT EDIT THIS FILE - This file was generated by the XML/Html & Property emitter -->
<!-- BEGIN MESSAGES -->
<Message ID="CWXDG7751I" severity="I" prefix="yes">
  <MsgText pgmKey="CWXDG_I_WSBatchPackager_InstallBegin" varFormat="Java">
    CWXDG_I_WSBatchPackager_InstallBegin=CWXDG7751I: 正在对应用程序 {0} 进行打包。
  </MsgText>
  <Explanation>
    表明已开始对指定的应用程序进行打包。
  </Explanation>
  <UserResponse>
    用户无需执行任何操作。
  </UserResponse>
</Message>
<Message ID="CWXDG7757E" severity="E" prefix="yes">
  <MsgText pgmKey="CWXDG_E_WSBatchPackager_MissingParm" varFormat="Java">
    CWXDG_E_WSBatchPackager_MissingParm=CWXDG7757E: 缺少输入参数 {0}。
  </MsgText>
  <Explanation>
    表明由于缺少必需的输入参数，而未能成功完成打包。
  </Explanation>
  <UserResponse>
    请检查语法并指定所有必需参数。
  </UserResponse>
</Message>
<Message ID="CWXDG7755E" severity="E" prefix="yes">
  <MsgText pgmKey="CWXDG_E_WSBatchPackager_InvalidAppName" varFormat="Java">
    CWXDG_E_WSBatchPackager_InvalidAppName=CWXDG7755E: 应用程序名 {0} 无效。
  </MsgText>
  <Explanation>
    表明由于应用程序名无效，而未能成功完成打包。
  </Explanation>
  <UserResponse>
    请指定有效的应用程序名。
  </UserResponse>
</Message>
<Message ID="CWXDG7762E" severity="E" prefix="yes">
  <MsgText pgmKey="CWXDG_E_WSBatchPackager_ClassFileNotFound" varFormat="Java">
    CWXDG_E_WSBatchPackager_ClassFileNotFound=CWXDG7762E: 找不到类文件 {0}。
  </MsgText>
  <Explanation>
    表明由于找不到指定的类文件，而未能成功完成打包。
  </Explanation>
  <UserResponse>
    请指定有效的类文件名。
  </UserResponse>
</Message>
<Message ID="CWXDG7754E" severity="E" prefix="yes">
  <MsgText pgmKey="CWXDG_E_WSBatchPackager_Exception" varFormat="Java">
    CWXDG_E_WSBatchPackager_Exception=CWXDG7754E: 打包失败，因为发生了错误 {0}。
  </MsgText>
  <Explanation>
    表明由于发生了指定的错误，而未能成功完成打包。
  </Explanation>
  <UserResponse>
    请与 IBM 服务机构联系。
  </UserResponse>
</Message>
<Message ID="CWXDG7760E" severity="E" prefix="yes">
  <MsgText pgmKey="CWXDG_E_WSBatchPackager_DuplicateJNDIName" varFormat="Java">
    CWXDG_E_WSBatchPackager_DuplicateJNDIName=CWXDG7760E: JNDI 名称 {0} 重复。
  </MsgText>
  <Explanation>
    表明由于多次指定了同一个 JNDI 名称，而未能成功完成打包。
  </Explanation>
  <UserResponse>
    请确保软件包中的所有 JNDI 名称都是唯一的。
  </UserResponse>
</Message>
<Message ID="CWXDG7759E" severity="E" prefix="yes">
  <MsgText pgmKey="CWXDG_E_WSBatchPackager_BadSyntax2" varFormat="Java">
    CWXDG_E_WSBatchPackager_BadSyntax2=CWXDG7759E: 语法错误：{0}
  </MsgText>
  <Explanation>
    表明由于发生了指定的语法错误，而未能成功完成打包。
  </Explanation>
  <UserResponse>
    请检查语法并指定有效的语法。
  </UserResponse>
</Message>
<Message ID="CWXDG7752I" severity="I" prefix="yes">
  <MsgText pgmKey="CWXDG_I_WSBatchPackager_InstallEnded" varFormat="Java">
    CWXDG_I_WSBatchPackager_InstallEnded=CWXDG7752I: 已完成对应用程序 {0} 进行打包。
  </MsgText>
  <Explanation>
    表明已成功完成对指定的应用程序进行打包。
  </Explanation>
  <UserResponse>
    用户无需执行任何操作。
  </UserResponse>
</Message>
<Message ID="CWXDG7758E" severity="E" prefix="yes">
  <MsgText pgmKey="CWXDG_E_WSBatchPackager_BadSyntax1" varFormat="Java">
    CWXDG_E_WSBatchPackager_BadSyntax1=CWXDG7758E: 语法错误：文本为 {0}
  </MsgText>
  <Explanation>
    表明由于指定的命令文本存在语法错误，而未能成功完成打包。
  </Explanation>
  <UserResponse>
    请检查语法并指定有效的语法。
  </UserResponse>
</Message>
<Message ID="CWXDG7763I" severity="I" prefix="yes">
  <MsgText pgmKey="CWXDG_I_WSBatchPackager_Syntax" varFormat="Java">
    CWXDG_I_WSBatchPackager_Syntax=CWXDG7763I: 语法 {0}。
  </MsgText>
  <Explanation>
    表明命令语法有效。
  </Explanation>
  <UserResponse>
    用户无需执行任何操作。
  </UserResponse>
</Message>
<Message ID="CWXDG7753E" severity="E" prefix="yes">
  <MsgText pgmKey="CWXDG_E_WSBatchPackager_InstallFailed" varFormat="Java">
    CWXDG_E_WSBatchPackager_InstallFailed=CWXDG7753E: 对应用程序 {0} 进行打包失败。
  </MsgText>
  <Explanation>
    表明未能成功完成对指定的应用程序进行打包。
  </Explanation>
  <UserResponse>
    请更正附带消息所指示的问题。
  </UserResponse>
</Message>
<Message ID="CWXDG7761E" severity="E" prefix="yes">
  <MsgText pgmKey="CWXDG_E_WSBatchPackager_ClassNameNotValid" varFormat="Java">
    CWXDG_E_WSBatchPackager_ClassNameNotValid=CWXDG7761E: 类名 {0} 无效。
  </MsgText>
  <Explanation>
    表明由于指定的类名无效，而未能成功完成打包。
  </Explanation>
  <UserResponse>
    请指定有效的类名。
  </UserResponse>
</Message>
<Message ID="CWXDG7756E" severity="E" prefix="yes">
  <MsgText pgmKey="CWXDG_E_WSBatchPackager_InvalidEarName" varFormat="Java">
    CWXDG_E_WSBatchPackager_InvalidEarName=CWXDG7756E: 输出文件名 {0} 无效。
  </MsgText>
  <Explanation>
    表明由于输出文件名无效，而未能成功完成打包。
  </Explanation>
  <UserResponse>
    请指定有效的输出文件名。
  </UserResponse>
</Message>
<!-- END MESSAGES -->
</TMSSource>
