<?xml version="1.0" encoding="UTF-8"?>
<?xml-stylesheet type="text/css" href="../../resources/stylesheets/wasmsgxml.css"?>
<TMSSource name="TivoliMessages" tmsVersion="1.0" xml:lang="en">
<!-- CMVC MSG File Name = /com.ibm.osgi.jndi.fep/src/com/ibm/osgi/jndi/nls/jndiMessages.nlsprops -->
<!-- DO NOT EDIT THIS FILE - This file was generated by the XML/Html & Property emitter -->
<!-- BEGIN MESSAGES -->
<Message ID="CWSAG1001E" severity="E" prefix="yes">
  <MsgText pgmKey="OSGIJNDI0001E" varFormat="Java">
    OSGIJNDI0001E=CWSAG1001E: &#30332;&#29983;&#20839;&#37096;&#37679;&#35492;&#12290;&#25214;&#19981;&#21040; {0} &#30340;&#26381;&#21209;&#21443;&#29031;&#12290;
  </MsgText>
  <Explanation>
    CMSG0001
  </Explanation>
  <UserResponse>
    CMSG0002
  </UserResponse>
</Message>
<Message ID="CWSAG1004E" severity="E" prefix="yes">
  <MsgText pgmKey="OSGIJNDI0004E" varFormat="Java">
    OSGIJNDI0004E=CWSAG1004E: &#30332;&#29983;&#20839;&#37096;&#37679;&#35492;&#12290;&#28961;&#27861;&#24314;&#31435; InitialContextFactory&#12290;
  </MsgText>
  <Explanation>
    CMSG0001
  </Explanation>
  <UserResponse>
    CMSG0002
  </UserResponse>
</Message>
<Message ID="CWSAG1007E" severity="E" prefix="yes">
  <MsgText pgmKey="OSGIJNDI0007E" varFormat="Java">
    OSGIJNDI0007E=CWSAG1007E: &#30332;&#29983;&#20839;&#37096;&#37679;&#35492;&#12290;&#28961;&#27861;&#24478; {0} &#24314;&#31435;&#12300;&#29872;&#22659;&#23450;&#32681;&#12301;&#29289;&#20214;&#12290;
  </MsgText>
  <Explanation>
    CMSG0001
  </Explanation>
  <UserResponse>
    CMSG0002
  </UserResponse>
</Message>
<Message ID="CWSAG1002E" severity="E" prefix="yes">
  <MsgText pgmKey="OSGIJNDI0002E" varFormat="Java">
    OSGIJNDI0002E=CWSAG1002E: &#30332;&#29983;&#20839;&#37096;&#37679;&#35492;&#12290;&#25214;&#19981;&#21040;&#39006;&#21029; {0} &#20197;&#24314;&#31435; InitialContextFactory &#29289;&#20214;&#12290;
  </MsgText>
  <Explanation>
    CMSG0001
  </Explanation>
  <UserResponse>
    CMSG0002
  </UserResponse>
</Message>
<Message ID="CWSAG1005E" severity="E" prefix="yes">
  <MsgText pgmKey="OSGIJNDI0005E" varFormat="Java">
    OSGIJNDI0005E=CWSAG1005E: &#30332;&#29983;&#36215;&#22987;&#37679;&#35492;&#12290;&#24478; {0} &#20659;&#22238;&#30340;&#36215;&#22987;&#29872;&#22659;&#23450;&#32681;&#26159;&#31354;&#20540;&#12290;
  </MsgText>
  <Explanation>
    CMSG0001
  </Explanation>
  <UserResponse>
    CMSG0002
  </UserResponse>
</Message>
<Message ID="CWSAG1008E" severity="E" prefix="yes">
  <MsgText pgmKey="OSGIJNDI0008E" varFormat="Java">
    OSGIJNDI0008E=CWSAG1008E: &#30332;&#29983;&#20839;&#37096;&#37679;&#35492;&#12290;&#22039;&#35430;&#20351;&#29992; factory {1} &#24478;&#12300;URL &#32177;&#30446;&#12301;{0} &#21462;&#24471; URL &#29872;&#22659;&#23450;&#32681;&#26178;&#65292;&#25152;&#20659;&#22238;&#30340;&#29872;&#22659;&#23450;&#32681;&#28858;&#31354;&#20540;&#12290;
  </MsgText>
  <Explanation>
    CMSG0001
  </Explanation>
  <UserResponse>
    CMSG0002
  </UserResponse>
</Message>
<Message ID="CWSAG1003E" severity="E" prefix="yes">
  <MsgText pgmKey="OSGIJNDI0003E" varFormat="Java">
    OSGIJNDI0003E=CWSAG1003E: &#23559; InitialContextFactory &#39006;&#21029; {1} &#23526;&#20363;&#21270;&#26178;&#65292;&#30332;&#29983;&#30064;&#24120;&#29376;&#27841; {0}&#12290;
  </MsgText>
  <Explanation>
    CMSG0001
  </Explanation>
  <UserResponse>
    CMSG0002
  </UserResponse>
</Message>
<Message ID="CWSAG1006E" severity="E" prefix="yes">
  <MsgText pgmKey="OSGIJNDI0006E" varFormat="Java">
    OSGIJNDI0006E=CWSAG1006E: &#30332;&#29983;&#20839;&#37096;&#37679;&#35492;&#12290;&#22312; {0} &#20013;&#25214;&#19981;&#21040;&#36942;&#28670;&#22120;&#28858; {1} &#30340;&#26381;&#21209;&#21443;&#29031;
  </MsgText>
  <Explanation>
    CMSG0001
  </Explanation>
  <UserResponse>
    CMSG0002
  </UserResponse>
</Message>
<Message ID="CWSAG1009E" severity="E" prefix="yes">
  <MsgText pgmKey="OSGIJNDI0009E" varFormat="Java">
    OSGIJNDI0009E=CWSAG1009E: &#30332;&#29983;&#20839;&#37096;&#37679;&#35492;&#12290;&#22039;&#35430;&#24478;&#29872;&#22659;&#23450;&#32681;&#39006;&#21029;&#36617;&#20837;&#22120; &#21462;&#24471;&#12300;URL &#32177;&#30446;&#12301;{0} &#30340; URL &#29872;&#22659;&#23450;&#32681;&#26178;&#65292;&#25152;&#20659;&#22238;&#30340;&#29872;&#22659;&#23450;&#32681;&#28858;&#31354;&#20540;&#12290;
  </MsgText>
  <Explanation>
    CMSG0001
  </Explanation>
  <UserResponse>
    CMSG0002
  </UserResponse>
</Message>
<!-- END MESSAGES -->
</TMSSource>
